DumbTF/Activations.py
DumbTF/Layer.py
DumbTF/Losses.py
DumbTF/Model.py
DumbTF/Optimizer.py
DumbTF/__init__.py
DumbTF/test.py
Dumb_TF-0.0.3.dist-info/LICENSE
Dumb_TF-0.0.3.dist-info/METADATA
Dumb_TF-0.0.3.dist-info/WHEEL
Dumb_TF-0.0.3.dist-info/top_level.txt
Dumb_TF-0.0.3.dist-info/RECORD
